<?xml version="1.0" encoding="UTF-8"?>
<build-type xmlns:xsi="http://www.w3.org/2001/XMLSchema-instance" uuid="c0cd89f6-54d1-44c7-b735-b4789bbd6a34" xsi:noNamespaceSchemaLocation="https://www.jetbrains.com/teamcity/schemas/2021.1/project-config.xsd">
  <name>Обновление образов у песочниц</name>
  <description />
  <settings>
    <parameters />
    <build-runners />
    <vcs-settings>
      <vcs-entry-ref root-id="SandboxDocker_SandboxDockerManager_HttpsGithubComSerdcebolitSandboxDockerManagerRefsHeadsMaster" />
    </vcs-settings>
    <requirements />
    <build-triggers />
    <cleanup />
  </settings>
</build-type>

